notion_archive/__init__.py
notion_archive/config/__init__.py
notion_archive/core/__init__.py
notion_archive/core/archive.py
notion_archive/core/embeddings.py
notion_archive/core/parser.py
notion_archive/utils/__init__.py
notion_archive-0.1.0.dist-info/licenses/LICENSE
notion_archive-0.1.0.dist-info/METADATA
notion_archive-0.1.0.dist-info/WHEEL
notion_archive-0.1.0.dist-info/top_level.txt
notion_archive-0.1.0.dist-info/RECORD
