Metadata-Version: 2.4
Name: notion-archive
Version: 0.1.0
Summary: Simple semantic search for Notion HTML exports using AI embeddings
Home-page: https://github.com/otron-io/notion-archive
Author: Notion Archive Contributors
Author-email: hello@notion-archive.com
Project-URL: Bug Reports, https://github.com/otron-io/notion-archive/issues
Project-URL: Source, https://github.com/otron-io/notion-archive
Project-URL: Documentation, https://github.com/otron-io/notion-archive#readme
Keywords: notion,search,ai,embeddings,knowledge-base,vector-search,semantic-search
Classifier: Development Status :: 4 - Beta
Classifier: Intended Audience :: Developers
Classifier: License :: OSI Approved :: MIT License
Classifier: Operating System :: OS Independent
Classifier: Programming Language :: Python :: 3
Classifier: Programming Language :: Python :: 3.8
Classifier: Programming Language :: Python :: 3.9
Classifier: Programming Language :: Python :: 3.10
Classifier: Programming Language :: Python :: 3.11
Classifier: Programming Language :: Python :: 3.12
Classifier: Topic :: Software Development :: Libraries :: Python Modules
Classifier: Topic :: Text Processing :: Indexing
Classifier: Topic :: Scientific/Engineering :: Artificial Intelligence
Requires-Python: >=3.8
License-File: LICENSE
Requires-Dist: beautifulsoup4>=4.9.0
Requires-Dist: chromadb>=0.4.0
Requires-Dist: langchain>=0.1.0
Requires-Dist: numpy>=1.20.0
Requires-Dist: pathlib
Requires-Dist: sentence-transformers>=2.0.0
Provides-Extra: openai
Requires-Dist: openai>=1.0.0; extra == "openai"
Provides-Extra: dev
Requires-Dist: pytest>=6.0.0; extra == "dev"
Requires-Dist: pytest-cov>=2.10.0; extra == "dev"
Requires-Dist: black>=21.0.0; extra == "dev"
Requires-Dist: flake8>=3.8.0; extra == "dev"
Requires-Dist: mypy>=0.800; extra == "dev"
Provides-Extra: all
Requires-Dist: openai>=1.0.0; extra == "all"
Dynamic: author
Dynamic: author-email
Dynamic: classifier
Dynamic: description
Dynamic: description-content-type
Dynamic: home-page
Dynamic: keywords
Dynamic: license-file
Dynamic: project-url
Dynamic: provides-extra
Dynamic: requires-dist
Dynamic: requires-python
Dynamic: summary
